{
   "shreejoy":[
      {
         "name":"ginkgo",
         "versions":[
            "ten_gapps",
            "ten"
         ]
      },
      {
         "name":"willow",
         "versions":[
            "ten_gapps",
            "ten"
         ]
      }
   ],
   "subins":[
      {
         "name":"X00TD",
         "versions":[
            "ten_gapps",
            "ten"
         ]
      },
      {
         "name":"riva",
         "versions":[
            "ten_gapps",
            "ten"
         ]
      }
   ]
}
